clime_issue_spoilage/__init__.py
clime_issue_spoilage/args.py
clime_issue_spoilage/graph.py
clime_issue_spoilage/main.py
clime_issue_spoilage/version.py
clime_issue_spoilage-0.3.1.dist-info/LICENSE
clime_issue_spoilage-0.3.1.dist-info/METADATA
clime_issue_spoilage-0.3.1.dist-info/WHEEL
clime_issue_spoilage-0.3.1.dist-info/entry_points.txt
clime_issue_spoilage-0.3.1.dist-info/top_level.txt
clime_issue_spoilage-0.3.1.dist-info/RECORD
