Metadata-Version: 2.1
Name: clime-issue-spoilage
Version: 0.3.1
Summary: CLIME - Issue Spoilage
Home-page: https://ssl.cs.luc.edu/projects/metricsDashboard
Author: Software and Systems Laboratory - Loyola University Chicago
Author-email: ssl-metrics@ssl.luc.edu
License: Apache License 2.0
Project-URL: Bug Tracker, https://github.com/SoftwareSystemsLaboratory/clime-issue-spoilage/issues
Project-URL: GitHub Repository, https://github.com/SoftwareSystemsLaboratory/clime-issue-spoilage
Keywords: bugzilla,bus factor,bus factor,cloc,commits,commits,delta lines of code,engineering,git,git,github,github,gitlab,installable,issue density,issue density,issue spoilage,issues,issues,kloc,lines of code,longitudinal graphs,loyola university chicago,loyola,luc,metrics,metrics,mining,productivity,python,repository mining,repository,simple,sloccount,software engineering,software metrics,software systems laboratory,software,ssl,thousands of lines of code,tool,vcs
Platform: UNKNOWN
Requires-Python: >=3.9
License-File: LICENSE
Requires-Dist: intervaltree
Requires-Dist: numpy
Requires-Dist: matplotlib
Requires-Dist: pandas
Requires-Dist: progress
Requires-Dist: python-dateutil
Requires-Dist: requests
